imco/__init__.py
imco/compare_images.py
imco-0.1.4.dist-info/LICENSE
imco-0.1.4.dist-info/METADATA
imco-0.1.4.dist-info/WHEEL
imco-0.1.4.dist-info/top_level.txt
imco-0.1.4.dist-info/zip-safe
imco-0.1.4.dist-info/RECORD
